features/__init__.py
features/steps/__init__.py
features/steps/tutorial_steps.py
slayer/__init__.py
slayer/behave_executor.py
slayer/deactivated_environment.py
slayer/main.py
slayer/slayer_configuration.py
slayer/slayer_logger.py
slayer/slayer_runner.py
slayer/config/config.cfg
slayer/config/logger.yaml
slayer/lib/__init__.py
slayer/lib/common/__init__.py
slayer/lib/common/decorators.py
slayer/lib/common/rest/__init__.py
slayer/lib/common/rest/rest_client.py
slayer/lib/common/web/__init__.py
slayer/lib/common/web/page_object.py
slayer/reporter/__init__.py
slayer-0.1.0a11.dist-info/METADATA
slayer-0.1.0a11.dist-info/RECORD
slayer-0.1.0a11.dist-info/WHEEL
slayer-0.1.0a11.dist-info/top_level.txt
