Metadata-Version: 2.1
Name: slayer
Version: 0.1.0a11
Summary: Slayer... the QA Automation Framework that came to SLAY!
Home-page: https://github.com/FrancoLM/slayer
Author: Franco Martinez
Author-email: martinez.franco.leonardo@gmail.com
License: BSD
Requires-Dist: behave (>=1.2.6)
Requires-Dist: certifi (>=2018.4.16)
Requires-Dist: chardet (>=3.0.4)
Requires-Dist: configobj (>=5.0.6)
Requires-Dist: future (>=0.16.0)
Requires-Dist: idna (>=2.6)
Requires-Dist: parse (>=1.8.2)
Requires-Dist: parse-type (>=0.4.2)
Requires-Dist: PyYAML (>=3.12)
Requires-Dist: requests (>=2.18.4)
Requires-Dist: six (>=1.11.0)
Requires-Dist: urllib3 (>=1.22)
